KahootBot/KahootBot.py
KahootBot/__init__.py
KahootBot-29.10.17.5.dist-info/DESCRIPTION.rst
KahootBot-29.10.17.5.dist-info/METADATA
KahootBot-29.10.17.5.dist-info/RECORD
KahootBot-29.10.17.5.dist-info/WHEEL
KahootBot-29.10.17.5.dist-info/metadata.json
KahootBot-29.10.17.5.dist-info/top_level.txt
